textattack/__init__.py
textattack/__main__.py
textattack/attack.py
textattack/attack_args.py
textattack/attacker.py
textattack/augment_args.py
textattack/dataset_args.py
textattack/model_args.py
textattack/trainer.py
textattack/training_args.py
textattack/attack_recipes/__init__.py
textattack/attack_recipes/a2t_yoo_2021.py
textattack/attack_recipes/attack_recipe.py
textattack/attack_recipes/bae_garg_2019.py
textattack/attack_recipes/bert_attack_li_2020.py
textattack/attack_recipes/checklist_ribeiro_2020.py
textattack/attack_recipes/chinese_recipe.py
textattack/attack_recipes/clare_li_2020.py
textattack/attack_recipes/deepwordbug_gao_2018.py
textattack/attack_recipes/faster_genetic_algorithm_jia_2019.py
textattack/attack_recipes/french_recipe.py
textattack/attack_recipes/genetic_algorithm_alzantot_2018.py
textattack/attack_recipes/hotflip_ebrahimi_2017.py
textattack/attack_recipes/iga_wang_2019.py
textattack/attack_recipes/input_reduction_feng_2018.py
textattack/attack_recipes/kuleshov_2017.py
textattack/attack_recipes/morpheus_tan_2020.py
textattack/attack_recipes/pruthi_2019.py
textattack/attack_recipes/pso_zang_2020.py
textattack/attack_recipes/pwws_ren_2019.py
textattack/attack_recipes/seq2sick_cheng_2018_blackbox.py
textattack/attack_recipes/spanish_recipe.py
textattack/attack_recipes/textbugger_li_2018.py
textattack/attack_recipes/textfooler_jin_2019.py
textattack/attack_results/__init__.py
textattack/attack_results/attack_result.py
textattack/attack_results/failed_attack_result.py
textattack/attack_results/maximized_attack_result.py
textattack/attack_results/skipped_attack_result.py
textattack/attack_results/successful_attack_result.py
textattack/augmentation/__init__.py
textattack/augmentation/augmenter.py
textattack/augmentation/recipes.py
textattack/commands/__init__.py
textattack/commands/attack_command.py
textattack/commands/attack_resume_command.py
textattack/commands/augment_command.py
textattack/commands/benchmark_recipe_command.py
textattack-0.3.10.dist-info/LICENSE
textattack-0.3.10.dist-info/METADATA
textattack-0.3.10.dist-info/WHEEL
textattack-0.3.10.dist-info/entry_points.txt
textattack-0.3.10.dist-info/top_level.txt
textattack-0.3.10.dist-info/RECORD
