Metadata-Version: 2.1
Name: textattack
Version: 0.3.10
Summary: A library for generating text adversarial examples
Home-page: https://github.com/QData/textattack
Author: QData Lab at the University of Virginia
Author-email: jm8wx@virginia.edu
License: MIT
Classifier: Programming Language :: Python :: 3
Classifier: License :: OSI Approved :: MIT License
Classifier: Operating System :: OS Independent
Requires-Python: >=3.8
License-File: LICENSE
Requires-Dist: bert-score >=0.3.5
Requires-Dist: editdistance
Requires-Dist: flair
Requires-Dist: filelock
Requires-Dist: language-tool-python
Requires-Dist: lemminflect
Requires-Dist: lru-dict
Requires-Dist: datasets >=2.4.0
Requires-Dist: nltk
Requires-Dist: numpy >=1.21.0
Requires-Dist: pandas >=1.0.1
Requires-Dist: scipy >=1.4.1
Requires-Dist: torch !=1.8,>=1.7.0
Requires-Dist: transformers >=4.30.0
Requires-Dist: terminaltables
Requires-Dist: tqdm
Requires-Dist: word2number
Requires-Dist: num2words
Requires-Dist: more-itertools
Requires-Dist: pinyin >=0.4.0
Requires-Dist: jieba
Requires-Dist: OpenHowNet
Provides-Extra: dev
Requires-Dist: recommonmark ; extra == 'dev'
Requires-Dist: nbsphinx ; extra == 'dev'
Requires-Dist: sphinx-autobuild ; extra == 'dev'
Requires-Dist: sphinx-rtd-theme ; extra == 'dev'
Requires-Dist: sphinx-markdown-tables ; extra == 'dev'
Requires-Dist: sphinx-copybutton ; extra == 'dev'
Requires-Dist: black ==20.8b1 ; extra == 'dev'
Requires-Dist: docformatter ; extra == 'dev'
Requires-Dist: isort ==5.6.4 ; extra == 'dev'
Requires-Dist: flake8 ; extra == 'dev'
Requires-Dist: pytest ; extra == 'dev'
Requires-Dist: pytest-xdist ; extra == 'dev'
Requires-Dist: tensorflow >=2.9.1 ; extra == 'dev'
Requires-Dist: tensorflow-hub ; extra == 'dev'
Requires-Dist: tensorflow-text >=2.9.0 ; extra == 'dev'
Requires-Dist: tensorboardX ; extra == 'dev'
Requires-Dist: tensorflow-estimator >=2.9.0 ; extra == 'dev'
Requires-Dist: sentence-transformers ==2.2.0 ; extra == 'dev'
Requires-Dist: stanza ; extra == 'dev'
Requires-Dist: visdom ; extra == 'dev'
Requires-Dist: wandb ; extra == 'dev'
Requires-Dist: gensim ; extra == 'dev'
Provides-Extra: docs
Requires-Dist: recommonmark ; extra == 'docs'
Requires-Dist: nbsphinx ; extra == 'docs'
Requires-Dist: sphinx-autobuild ; extra == 'docs'
Requires-Dist: sphinx-rtd-theme ; extra == 'docs'
Requires-Dist: sphinx-markdown-tables ; extra == 'docs'
Requires-Dist: sphinx-copybutton ; extra == 'docs'
Provides-Extra: optional
Requires-Dist: sentence-transformers ==2.2.0 ; extra == 'optional'
Requires-Dist: stanza ; extra == 'optional'
Requires-Dist: visdom ; extra == 'optional'
Requires-Dist: wandb ; extra == 'optional'
Requires-Dist: gensim ; extra == 'optional'
Provides-Extra: tensorflow
Requires-Dist: tensorflow >=2.9.1 ; extra == 'tensorflow'
Requires-Dist: tensorflow-hub ; extra == 'tensorflow'
Requires-Dist: tensorflow-text >=2.9.0 ; extra == 'tensorflow'
Requires-Dist: tensorboardX ; extra == 'tensorflow'
Requires-Dist: tensorflow-estimator >=2.9.0 ; extra == 'tensorflow'
Provides-Extra: test
Requires-Dist: black ==20.8b1 ; extra == 'test'
Requires-Dist: docformatter ; extra == 'test'
Requires-Dist: isort ==5.6.4 ; extra == 'test'
Requires-Dist: flake8 ; extra == 'test'
Requires-Dist: pytest ; extra == 'test'
Requires-Dist: pytest-xdist ; extra == 'test'
